[
  {
    "name": "AMAZON__SEARCH_PRODUCTS",
    "description": "Searches Amazon for a keyword and returns a list of products. Allows sorting and filtering for deals.",
    "tags": ["amazon", "search", "product", "shopping", "find", "ecommerce"],
    "visibility": "public",
    "active": true,
    "protocol": "connector",
    "protocol_data": {},
    "parameters": {
      "type": "object",
      "properties": {
        "keyword": {
          "type": "string",
          "description": "The search term or product name to look for (e.g., 'wireless headphones')."
        },
        "num_results": {
          "type": "integer",
          "description": "The desired number of products to return. Defaults to 20."
        },
        "sort_by": {
          "type": "string",
          "description": "The sorting order for the results. Available options: 'FEATURED', 'PRICE_LOW_TO_HIGH', 'PRICE_HIGH_TO_LOW', 'REVIEW_RANK', 'NEWEST_ARRIVALS', 'BEST_SELLERS'. Defaults to 'FEATURED'."
        },
        "find_deals": {
          "type": "boolean",
          "description": "Set to true to search only within Amazon's 'Today's Deals'. Defaults to false."
        }
      },
      "required": ["keyword"],
      "visible": ["keyword", "num_results", "sort_by", "find_deals"],
      "additionalProperties": false
    }
  },
  {
    "name": "AMAZON__GET_PRODUCT_DETAILS",
    "description": "Fetches and parses detailed information from a single Amazon product page URL.",
    "tags": ["amazon", "product", "details", "scrape", "info", "ecommerce"],
    "visibility": "public",
    "active": true,
    "protocol": "connector",
    "protocol_data": {},
    "parameters": {
      "type": "object",
      "properties": {
        "product_url": {
          "type": "string",
          "description": "The full URL of the Amazon product page you want details for."
        }
      },
      "required": ["product_url"],
      "visible": ["product_url"],
      "additionalProperties": false
    }
  }
]
